bluer_ugv/__init__.py
bluer_ugv/__main__.py
bluer_ugv/config.env
bluer_ugv/env.py
bluer_ugv/host.py
bluer_ugv/logger.py
bluer_ugv/sample.env
bluer_ugv/urls.py
bluer_ugv/.abcli/abcli.sh
bluer_ugv/.abcli/actions.sh
bluer_ugv/.abcli/aka.sh
bluer_ugv/.abcli/alias.sh
bluer_ugv/.abcli/bluer_UGV.sh
bluer_ugv/.abcli/swallow.sh
bluer_ugv/.abcli/swallow/dataset.sh
bluer_ugv/.abcli/swallow/debug.sh
bluer_ugv/.abcli/swallow/env.sh
bluer_ugv/.abcli/swallow/ethernet.sh
bluer_ugv/.abcli/swallow/git.sh
bluer_ugv/.abcli/swallow/keyboard.sh
bluer_ugv/.abcli/swallow/select_target.sh
bluer_ugv/.abcli/swallow/session.sh
bluer_ugv/.abcli/swallow/ultrasonic.sh
bluer_ugv/.abcli/swallow/video.sh
bluer_ugv/.abcli/swallow/dataset/combine.sh
bluer_ugv/.abcli/swallow/dataset/download.sh
bluer_ugv/.abcli/swallow/dataset/edit.sh
bluer_ugv/.abcli/swallow/dataset/list.sh
bluer_ugv/.abcli/swallow/dataset/upload.sh
bluer_ugv/.abcli/swallow/env/cat.sh
bluer_ugv/.abcli/swallow/env/cd.sh
bluer_ugv/.abcli/swallow/env/cp.sh
bluer_ugv/.abcli/swallow/env/list.sh
bluer_ugv/.abcli/swallow/env/set.sh
bluer_ugv/.abcli/swallow/ethernet/test.sh
bluer_ugv/.abcli/swallow/git/rm_keys.sh
bluer_ugv/.abcli/swallow/keyboard/test.sh
bluer_ugv/.abcli/swallow/ultrasonic/review.sh
bluer_ugv/.abcli/swallow/ultrasonic/test.sh
bluer_ugv/.abcli/swallow/video/play.sh
bluer_ugv/.abcli/swallow/video/playlist.sh
bluer_ugv/.abcli/swallow/video/playlist/cat.sh
bluer_ugv/.abcli/swallow/video/playlist/download.sh
bluer_ugv/.abcli/swallow/video/playlist/edit.sh
bluer_ugv/.abcli/swallow/video/playlist/upload.sh
bluer_ugv/.abcli/tests/README.sh
bluer_ugv/.abcli/tests/help.sh
bluer_ugv/.abcli/tests/swallow_dataset_combine.sh
bluer_ugv/.abcli/tests/swallow_dataset_combine_explicit.sh
bluer_ugv/.abcli/tests/swallow_dataset_combine_sequence.sh
bluer_ugv/.abcli/tests/swallow_dataset_download_upload.sh
bluer_ugv/.abcli/tests/swallow_dataset_edit.sh
bluer_ugv/.abcli/tests/swallow_dataset_list.sh
bluer_ugv/.abcli/tests/swallow_video_play.sh
bluer_ugv-7.846.1.dist-info/licenses/LICENSE
bluer_ugv-7.846.1.dist-info/METADATA
bluer_ugv-7.846.1.dist-info/WHEEL
bluer_ugv-7.846.1.dist-info/top_level.txt
bluer_ugv-7.846.1.dist-info/RECORD
