Metadata-Version: 2.4
Name: bluer_ugv
Version: 7.846.1
Summary: 🐬 AI x UGV.
Home-page: https://github.com/kamangir/bluer-ugv
Author: Arash Abadpour (Kamangir)
Author-email: arash.abadpour@gmail.com
License: CC0-1.0
Classifier: Programming Language :: Python :: 3
Classifier: Programming Language :: Unix Shell
Classifier: Operating System :: OS Independent
License-File: LICENSE
Requires-Dist: bluer_ai
Requires-Dist: bluer_agent
Requires-Dist: bluer_algo
Requires-Dist: bluer_sbc
Requires-Dist: keyboard
Requires-Dist: ipdb
Dynamic: author
Dynamic: author-email
Dynamic: classifier
Dynamic: description
Dynamic: description-content-type
Dynamic: home-page
Dynamic: license
Dynamic: license-file
Dynamic: requires-dist
Dynamic: summary
